tinykit/__init__.py
tinykit/db.py
tinykit/models.py
tinykit/version.py
tinykit-0.2.0.dist-info/LICENSE
tinykit-0.2.0.dist-info/METADATA
tinykit-0.2.0.dist-info/WHEEL
tinykit-0.2.0.dist-info/top_level.txt
tinykit-0.2.0.dist-info/RECORD
