Metadata-Version: 2.1
Name: tinykit
Version: 0.2.0
Summary: UNKNOWN
Home-page: http://github.com/iromli/tinykit
Author: Isman Firmansyah
Author-email: isman.firmansyah@gmail.com
License: MIT
Platform: UNKNOWN
Classifier: Intended Audience :: Developers
Classifier: License :: OSI Approved :: MIT License
Classifier: Topic :: Software Development :: Libraries :: Python Modules
Classifier: Programming Language :: Python
Classifier: Programming Language :: Python :: 3
License-File: LICENSE
Requires-Dist: jsonmodels
Requires-Dist: tinydb
Requires-Dist: tinyrecord
